Metadata-Version: 2.1
Name: text-processing
Version: 0.0.2
Summary: Text processing helpers
Home-page: https://github.com/N2BBrasil/text-processing
Author: Samuel Heinrichs
Author-email: samuel@n2bbrasil.com
License: UNKNOWN
Platform: UNKNOWN
Classifier: Programming Language :: Python :: 3
Classifier: License :: OSI Approved :: MIT License
Classifier: Operating System :: OS Independent
